char_lcd/__init__.py
char_lcd/pcd8544.py
char_lcd-2.0.dist-info/DESCRIPTION.rst
char_lcd-2.0.dist-info/METADATA
char_lcd-2.0.dist-info/RECORD
char_lcd-2.0.dist-info/WHEEL
char_lcd-2.0.dist-info/metadata.json
char_lcd-2.0.dist-info/top_level.txt
