Metadata-Version: 2.0
Name: char-lcd
Version: 2.0
Summary: Library to drive character LCD display and plate.
Home-page: https://github.com/llazzaro/char_lcd
Author: Leonardo Lazzaro
Author-email: lazzaroleonardo@gmail.com
License: MIT
Platform: UNKNOWN
Classifier: Development Status :: 4 - Beta
Classifier: Operating System :: POSIX :: Linux
Classifier: License :: OSI Approved :: MIT License
Classifier: Intended Audience :: Developers
Classifier: Programming Language :: Python :: 2.7
Classifier: Programming Language :: Python :: 3
Classifier: Topic :: Software Development
Classifier: Topic :: System :: Hardware
Requires-Dist: pygpio
